{"assets/.DS_Store":["assets/.DS_Store","assets/images/home/.DS_Store","assets/images/.DS_Store"],"assets/fonts/Raleway-Black.ttf":["assets/fonts/Raleway-Black.ttf"],"assets/fonts/Raleway-MediumItalic.ttf":["assets/fonts/Raleway-MediumItalic.ttf"],"assets/fonts/Raleway-SemiBold.ttf":["assets/fonts/Raleway-SemiBold.ttf"],"assets/images/home/.DS_Store":["assets/images/home/.DS_Store"],"assets/images/home/clock.png":["assets/images/home/clock.png"],"assets/images/home/menu.svg":["assets/images/home/menu.svg"],"assets/images/home/search.svg":["assets/images/home/search.svg"],"packages/cupertino_icons/assets/CupertinoIcons.ttf":["packages/cupertino_icons/assets/CupertinoIcons.ttf"]}